{
    "expenses":[
        {
            "id": "e1",
            "title": "Testing",
            "amount": 123,
            "date": "2023, 01, 01"
        },
        {
            "id": "e2",
            "title": "Testing2",
            "amount": 234,
            "date": "2023, 01, 01"
        },
        {
            "id": "e3",
            "title": "Testing3",
            "amount": 345,
            "date": "2023, 01, 01"
        },
        {
            "id": "e4",
            "title": "Testing4",
            "amount": 456,
            "date": "2023, 04, 01"
        }
    ]
}